ppieces/__init__.py
ppieces/main.py
ppieces/version.py
ppieces/django/.gitignore
ppieces/django/pre-commit-config.yaml
ppieces/scripts/setup_autoenv.sh
ppieces/templates/.djlintrc
ppieces/templates/.gitignore
ppieces/templates/.pre-commit-config.yaml
ppieces/templates/.ruff.toml
ppieces/templates/Makefile
ppieces/templates/README-sample.md
ppieces/templates/main.py
ppieces/templates/requirements.txt
ppieces/templates/pip-tools/Makefile
ppieces/templates/pip-tools/requirements/base.in
ppieces/templates/pip-tools/requirements/development.in
ppieces/templates/pip-tools/requirements/production.in
ppieces/templates/pip-tools/requirements/test.in
ppieces/utils/__init__.py
ppieces/utils/cli.py
ppieces/utils/commands.py
ppieces/utils/constants.py
ppieces/utils/copy.py
ppieces/utils/flows.py
ppieces/utils/prompts.py
ppieces/utils/validation.py
ppieces-0.5.2.dist-info/LICENSE
ppieces-0.5.2.dist-info/METADATA
ppieces-0.5.2.dist-info/WHEEL
ppieces-0.5.2.dist-info/entry_points.txt
ppieces-0.5.2.dist-info/top_level.txt
ppieces-0.5.2.dist-info/RECORD
