Metadata-Version: 2.1
Name: ppieces
Version: 0.5.2
Summary: A command-line utility to streamline the setup of new Python projects.
Author-email: Patilla Code <patillacode@gmail.com>
License: MIT
Project-URL: homepage, https://github.com/patillacode/ppieces
Project-URL: repository, https://github.com/patillacode/ppieces
Classifier: Programming Language :: Python :: 3
Classifier: License :: OSI Approved :: MIT License
Classifier: Operating System :: OS Independent
Requires-Python: >=3.10
License-File: LICENSE
Requires-Dist: click ==8.1.7
Requires-Dist: markdown-it-py ==3.0.0
Requires-Dist: mdurl ==0.1.2
Requires-Dist: pyfiglet ==1.0.2
Requires-Dist: pygments ==2.17.2
Requires-Dist: rich ==13.7.0
Requires-Dist: termcolor ==2.4.0
Provides-Extra: test
Requires-Dist: asttokens ==2.4.1 ; extra == 'test'
Requires-Dist: build ==1.0.3 ; extra == 'test'
Requires-Dist: cfgv ==3.4.0 ; extra == 'test'
Requires-Dist: click ==8.1.7 ; extra == 'test'
Requires-Dist: colorama ==0.4.6 ; extra == 'test'
Requires-Dist: distlib ==0.3.8 ; extra == 'test'
Requires-Dist: executing ==2.0.1 ; extra == 'test'
Requires-Dist: filelock ==3.13.1 ; extra == 'test'
Requires-Dist: icecream ==2.1.3 ; extra == 'test'
Requires-Dist: identify ==2.5.33 ; extra == 'test'
Requires-Dist: markdown-it-py ==3.0.0 ; extra == 'test'
Requires-Dist: mdurl ==0.1.2 ; extra == 'test'
Requires-Dist: nodeenv ==1.8.0 ; extra == 'test'
Requires-Dist: packaging ==23.2 ; extra == 'test'
Requires-Dist: pip-tools ==7.3.0 ; extra == 'test'
Requires-Dist: platformdirs ==4.2.0 ; extra == 'test'
Requires-Dist: pre-commit ==3.6.0 ; extra == 'test'
Requires-Dist: pyfiglet ==1.0.2 ; extra == 'test'
Requires-Dist: pygments ==2.17.2 ; extra == 'test'
Requires-Dist: pyproject-hooks ==1.0.0 ; extra == 'test'
Requires-Dist: pyyaml ==6.0.1 ; extra == 'test'
Requires-Dist: rich ==13.7.0 ; extra == 'test'
Requires-Dist: six ==1.16.0 ; extra == 'test'
Requires-Dist: termcolor ==2.4.0 ; extra == 'test'
Requires-Dist: virtualenv ==20.25.0 ; extra == 'test'
Requires-Dist: wheel ==0.42.0 ; extra == 'test'
Requires-Dist: coverage ==7.4.1 ; extra == 'test'
Requires-Dist: iniconfig ==2.0.0 ; extra == 'test'
Requires-Dist: pluggy ==1.4.0 ; extra == 'test'
Requires-Dist: pytest ==8.0.0 ; extra == 'test'
Requires-Dist: pytest-click ==1.1.0 ; extra == 'test'
Requires-Dist: pytest-mock ==3.12.0 ; extra == 'test'
